optical_ray_tracer/__init__.py
optical_ray_tracer/configurations/__init__.py
optical_ray_tracer/configurations/main.py
optical_ray_tracer/configurations/geometries/Cylindric.py
optical_ray_tracer/configurations/geometries/Parabolic.py
optical_ray_tracer/configurations/geometries/__init__.py
optical_ray_tracer/configurations/geometries/given_geometry.py
optical_ray_tracer/configurations/geometries/ring_array.py
optical_ray_tracer/main/__init__.py
optical_ray_tracer/main/main.py
optical_ray_tracer/rays/__init__.py
optical_ray_tracer/rays/main.py
optical_ray_tracer/rays/raytracer/__init__.py
optical_ray_tracer/rays/raytracer/ray_tracer.py
optical_ray_tracer/rays/source/__init__.py
optical_ray_tracer/rays/source/large_source.py
optical_ray_tracer/rays/source/main.py
optical_ray_tracer/rays/source/point_source.py
optical_ray_tracer/tests/__init__.py
optical_ray_tracer/tests/test_main.py
optical_ray_tracer/tests/test_parabolique.py
optical_ray_tracer/utils/__init__.py
optical_ray_tracer/utils/rotation_vect.py
optical_ray_tracer/utils/sphericalcartesian.py
optical_ray_tracer-1.4.0.dist-info/licenses/LICENSE
optical_ray_tracer-1.4.0.dist-info/METADATA
optical_ray_tracer-1.4.0.dist-info/WHEEL
optical_ray_tracer-1.4.0.dist-info/top_level.txt
optical_ray_tracer-1.4.0.dist-info/RECORD
