Metadata-Version: 2.4
Name: optical-ray-tracer
Version: 1.4.0
Summary: Scientific package for optical ray tracing simulations.
Home-page: https://github.com/Damzo/optical_ray_collector
Author: Dam-Bè L. DOUTI, Henoc N'GASAMA, Serge DZO
Author-email: ngasamah@gmail.com
License: GPLv3
Keywords: optics ray-tracing simulation physics
Classifier: Development Status :: 4 - Beta
Classifier: Intended Audience :: Science/Research
Classifier: License :: OSI Approved :: GNU General Public License v3 (GPLv3)
Classifier: Operating System :: OS Independent
Classifier: Programming Language :: Python :: 3
Classifier: Topic :: Scientific/Engineering :: Physics
Requires-Python: >=3.8
License-File: LICENSE
Requires-Dist: matplotlib>=3.4
Requires-Dist: numpy>=1.21
Requires-Dist: pandas>=1.3
Requires-Dist: scipy>=1.7
Requires-Dist: sympy>=1.9
Requires-Dist: numba>=0.55
Dynamic: author
Dynamic: author-email
Dynamic: classifier
Dynamic: description
Dynamic: description-content-type
Dynamic: home-page
Dynamic: keywords
Dynamic: license
Dynamic: license-file
Dynamic: requires-dist
Dynamic: requires-python
Dynamic: summary
